rocon_client_sdk_py/__init__.py
rocon_client_sdk_py/const.py
rocon_client_sdk_py/info.py
rocon_client_sdk_py/virtual_worker.py
rocon_client_sdk_py/worker.py
rocon_client_sdk_py/worker_client.py
rocon_client_sdk_py/core_logic/__init__.py
rocon_client_sdk_py/core_logic/action.py
rocon_client_sdk_py/core_logic/action_manager.py
rocon_client_sdk_py/core_logic/context.py
rocon_client_sdk_py/core_logic/hook.py
rocon_client_sdk_py/core_logic/hook_manager.py
rocon_client_sdk_py/core_logic/hook_origin_check_revision.py
rocon_client_sdk_py/core_logic/hook_origin_init_worker.py
rocon_client_sdk_py/core_logic/hook_origin_validate_report.py
rocon_client_sdk_py/core_logic/map_manager.py
rocon_client_sdk_py/core_logic/message.py
rocon_client_sdk_py/core_logic/message_manager.py
rocon_client_sdk_py/core_logic/trees/__init__.py
rocon_client_sdk_py/core_logic/trees/behavior_tree_manager.py
rocon_client_sdk_py/core_logic/trees/blackboard_manager.py
rocon_client_sdk_py/core_logic/trees/constants.py
rocon_client_sdk_py/core_logic/trees/deco.py
rocon_client_sdk_py/core_logic/trees/task.py
rocon_client_sdk_py/core_logic/trees/tasks_bootstrap.py
rocon_client_sdk_py/core_logic/trees/tasks_busy_status.py
rocon_client_sdk_py/core_logic/trees/tasks_check_life_cycle.py
rocon_client_sdk_py/core_logic/trees/tasks_external_control.py
rocon_client_sdk_py/core_logic/trees/tasks_heart_beat.py
rocon_client_sdk_py/core_logic/trees/tasks_idle_status.py
rocon_client_sdk_py/core_logic/trees/tasks_offline_error.py
rocon_client_sdk_py/core_logic/trees/tasks_test.py
rocon_client_sdk_py/core_logic/trees/trees_manager.py
rocon_client_sdk_py/logger/__init__.py
rocon_client_sdk_py/logger/rocon_logger.py
rocon_client_sdk_py/rocon_apis/__init__.py
rocon_client_sdk_py/rocon_apis/api.py
rocon_client_sdk_py/rocon_apis/api_configuration.py
rocon_client_sdk_py/rocon_apis/api_report.py
rocon_client_sdk_py/rocon_apis/api_site_configuration.py
rocon_client_sdk_py/rocon_apis/api_task.py
rocon_client_sdk_py-0.5.15.dist-info/LICENSE
rocon_client_sdk_py-0.5.15.dist-info/METADATA
rocon_client_sdk_py-0.5.15.dist-info/WHEEL
rocon_client_sdk_py-0.5.15.dist-info/top_level.txt
rocon_client_sdk_py-0.5.15.dist-info/RECORD
