Metadata-Version: 2.1
Name: rocon-client-sdk-py
Version: 0.5.15
Summary: Rocon Client SDK for Python
Home-page: https://github.com/boklae/rocon_client_sdk_py
Author: YUJIN ROBOT Co.,Ltd.
Author-email: blcho@yujinrobot.com
License: UNKNOWN
Download-URL: https://github.com/boklae/rocon_client_sdk_py/archive/master.zip
Keywords: rocon_client_sdk,rocon_client_sdk_py
Platform: UNKNOWN
Classifier: Development Status :: 2 - Pre-Alpha
Classifier: Intended Audience :: Developers
Classifier: License :: OSI Approved :: MIT License
Classifier: Natural Language :: English
Classifier: Programming Language :: Python :: 3.6
Classifier: Programming Language :: Python :: 3.7
Requires-Python: >=3.6
Requires-Dist: aiohttp (==3.6.2)
Requires-Dist: pathfinding (==0.0.4)
Requires-Dist: Pillow (==7.0.0)
Requires-Dist: py-trees (==2.0.6)
Requires-Dist: pydash (==4.7.6)
Requires-Dist: PyYAML (==5.3)
Requires-Dist: paho-mqtt (==1.5.0)
Requires-Dist: Rx (==3.0.1)
Requires-Dist: overrides (==2.8.0)
Requires-Dist: psutil (==5.7.0)
